metallum.py
python_metallum-1.1.0.dist-info/LICENSE
python_metallum-1.1.0.dist-info/METADATA
python_metallum-1.1.0.dist-info/WHEEL
python_metallum-1.1.0.dist-info/top_level.txt
python_metallum-1.1.0.dist-info/RECORD
