Metadata-Version: 2.1
Name: python-metallum
Version: 1.1.0
Summary: Python API for www.metal-archives.com
Home-page: https://github.com/lcharlick/python-metallum
Author: Lachlan Charlick
Author-email: lachlan.charlick@gmail.com
License: MIT
Platform: UNKNOWN
Requires-Python: >=3
Requires-Dist: requests
Requires-Dist: requests-cache
Requires-Dist: pyquery
Requires-Dist: python-dateutil
